{
    "version": "0.4",
    "title": "Header (White)",
    "type": "section",
    "metadata": {
        "template_type": "section-header",
        "include_in_zip": "1",
        "elementor_pro_required": null,
        "wp_page_template": "elementor_canvas"
    },
    "content": [
        {
            "id": "1ae767c2",
            "settings": {
                "structure": "20",
                "margin": {
                    "unit": "px",
                    "top": "0",
                    "right": 0,
                    "bottom": "-105",
                    "left": 0,
                    "isLinked": false
                },
                "margin_mobile": {
                    "unit": "px",
                    "top": "0",
                    "right": 0,
                    "bottom": "-59",
                    "left": 0,
                    "isLinked": false
                },
                "z_index": 10,
                "margin_tablet": {
                    "unit": "px",
                    "top": "0",
                    "right": 0,
                    "bottom": "-70",
                    "left": 0,
                    "isLinked": false
                },
                "_title": "Header",
                "padding_tablet": {
                    "unit": "px",
                    "top": "15",
                    "right": "30",
                    "bottom": "0",
                    "left": "30",
                    "isLinked": false
                },
                "padding_mobile": {
                    "unit": "px",
                    "top": "10",
                    "right": "20",
                    "bottom": "0",
                    "left": "20",
                    "isLinked": false
                },
                "premium_eq_height_switcher": "",
                "premium_eq_height_type": "widget",
                "premium_eq_height_target": "",
                "premium_eq_height_custom_target": "",
                "premium_eq_height_enable_on": [
                    "desktop",
                    "tablet",
                    "mobile"
                ],
                "background_background": "classic",
                "padding": {
                    "unit": "px",
                    "top": "5",
                    "right": "0",
                    "bottom": "0",
                    "left": "0",
                    "isLinked": false
                },
                "__globals__": {
                    "background_color": ""
                },
                "animation": "fadeIn"
            },
            "elements": [
                {
                    "id": "76bf856a",
                    "settings": {
                        "_column_size": 50,
                        "_inline_size": 8.258,
                        "content_position": "center",
                        "_inline_size_mobile": 20,
                        "animation": "fadeIn",
                        "animation_delay": 200,
                        "padding": {
                            "unit": "px",
                            "top": "0",
                            "right": "0",
                            "bottom": "0",
                            "left": "0",
                            "isLinked": false
                        }
                    },
                    "elements": [
                        {
                            "id": "69924922",
                            "settings": {
                                "image": {
                                    "url": "http:\/\/askproject.net\/bankai\/wp-content\/uploads\/sites\/32\/2021\/10\/logo_Asset-1_2.png",
                                    "id": 172,
                                    "alt": "",
                                    "source": "library"
                                },
                                "align": "left",
                                "width": {
                                    "unit": "%",
                                    "size": 45,
                                    "sizes": []
                                },
                                "_border_border": "solid",
                                "_border_width": {
                                    "unit": "px",
                                    "top": "0",
                                    "right": "1",
                                    "bottom": "0",
                                    "left": "0",
                                    "isLinked": false
                                },
                                "_border_color": "#FFFFFF52",
                                "_border_width_tablet": {
                                    "unit": "px",
                                    "top": "0",
                                    "right": "0",
                                    "bottom": "0",
                                    "left": "0",
                                    "isLinked": false
                                },
                                "_border_width_mobile": {
                                    "unit": "px",
                                    "top": "0",
                                    "right": "0",
                                    "bottom": "0",
                                    "left": "0",
                                    "isLinked": false
                                },
                                "width_mobile": {
                                    "unit": "%",
                                    "size": 55,
                                    "sizes": []
                                },
                                "caption_typography_line_height": {
                                    "unit": "em",
                                    "size": "",
                                    "sizes": []
                                },
                                "width_tablet": {
                                    "unit": "%",
                                    "size": 65,
                                    "sizes": []
                                },
                                "_margin_mobile": {
                                    "unit": "px",
                                    "top": "0",
                                    "right": "0",
                                    "bottom": "0",
                                    "left": "0",
                                    "isLinked": false
                                }
                            },
                            "elements": [],
                            "isInner": false,
                            "widgetType": "image",
                            "elType": "widget"
                        }
                    ],
                    "isInner": false,
                    "elType": "column"
                },
                {
                    "id": "3a0ae431",
                    "settings": {
                        "_column_size": 50,
                        "_inline_size": 91.742,
                        "content_position": "center",
                        "_inline_size_mobile": 80,
                        "padding_mobile": {
                            "unit": "px",
                            "top": "0",
                            "right": "0",
                            "bottom": "0",
                            "left": "0",
                            "isLinked": false
                        },
                        "padding": {
                            "unit": "px",
                            "top": "0",
                            "right": "0",
                            "bottom": "0",
                            "left": "0",
                            "isLinked": false
                        }
                    },
                    "elements": [
                        {
                            "id": "4ed92ede",
                            "settings": {
                                "structure": "20",
                                "layout": "full_width",
                                "reverse_order_tablet": "reverse-tablet",
                                "reverse_order_mobile": "reverse-mobile",
                                "premium_eq_height_switcher": "",
                                "premium_eq_height_type": "widget",
                                "premium_eq_height_target": "",
                                "premium_eq_height_custom_target": "",
                                "premium_eq_height_enable_on": [
                                    "desktop",
                                    "tablet",
                                    "mobile"
                                ]
                            },
                            "elements": [
                                {
                                    "id": "e50466d",
                                    "settings": {
                                        "_column_size": 50,
                                        "_inline_size": 74.831,
                                        "content_position": "center",
                                        "_inline_size_tablet": 8,
                                        "_inline_size_mobile": 25,
                                        "content_position_mobile": "center",
                                        "margin_tablet": {
                                            "unit": "px",
                                            "top": "0",
                                            "right": "0",
                                            "bottom": "0",
                                            "left": "0",
                                            "isLinked": false
                                        }
                                    },
                                    "elements": [
                                        {
                                            "id": "7e442fa",
                                            "settings": {
                                                "elementskit_submenu_container_width": "200px",
                                                "elementskit_nav_menu": "header",
                                                "elementskit_hamburger_icon": {
                                                    "value": "icon icon-menu-11",
                                                    "library": "ekiticons"
                                                },
                                                "elementskit_one_page_enable": "",
                                                "elementskit_menubar_background_color": "#0D133300",
                                                "wrapper_color_mobile_tablet": "#0F0F0F",
                                                "elementskit_menu_text_color": "#FFFFFF8A",
                                                "elementskit_item_background_hover_background": "classic",
                                                "elementskit_item_background_hover_color": "#E2000100",
                                                "elementskit_nav_menu_active_bg_color_background": "classic",
                                                "elementskit_nav_menu_active_bg_color_color": "#FFFFFF00",
                                                "elementskit_menu_item_spacing": {
                                                    "unit": "px",
                                                    "top": "0",
                                                    "right": "20",
                                                    "bottom": "0",
                                                    "left": "20",
                                                    "isLinked": false
                                                },
                                                "elementskit_menu_item_spacing_tablet": {
                                                    "unit": "px",
                                                    "top": "5",
                                                    "right": "15",
                                                    "bottom": "5",
                                                    "left": "30",
                                                    "isLinked": false
                                                },
                                                "elementskit_style_tab_submenu_indicator_color_tablet": "#474747",
                                                "elementskit_style_tab_submenu_indicator_color_mobile": "#545454",
                                                "elementskit_submenu_item_spacing": {
                                                    "unit": "px",
                                                    "top": "1",
                                                    "right": "15",
                                                    "bottom": "1",
                                                    "left": "35",
                                                    "isLinked": false
                                                },
                                                "elementskit_menu_item_background_background": "classic",
                                                "elementskit_menu_item_background_color": "#02010100",
                                                "elementskit_item_text_color_hover_tablet": "#FFFFFF",
                                                "elementskit_menu_item_background_hover_background": "classic",
                                                "elementskit_menu_item_background_hover_color": "#02010100",
                                                "elementskit_nav_sub_menu_active_bg_color_background": "classic",
                                                "elementskit_nav_sub_menu_active_bg_color_color": "#02010100",
                                                "elementskit_menu_item_border_border": "solid",
                                                "elementskit_menu_item_border_width_tablet": {
                                                    "unit": "px",
                                                    "top": "0",
                                                    "right": "0",
                                                    "bottom": "0",
                                                    "left": "0",
                                                    "isLinked": false
                                                },
                                                "elementskit_menu_item_border_color": "#02010100",
                                                "elementskit_menu_item_border_last_child_border": "solid",
                                                "elementskit_menu_item_border_last_child_width_tablet": {
                                                    "unit": "px",
                                                    "top": "0",
                                                    "right": "0",
                                                    "bottom": "0",
                                                    "left": "0",
                                                    "isLinked": false
                                                },
                                                "elementskit_menu_item_border_last_child_color": "#02010100",
                                                "elementskit_menu_item_border_first_child_border": "solid",
                                                "elementskit_menu_item_border_first_child_width_tablet": {
                                                    "unit": "px",
                                                    "top": "0",
                                                    "right": "0",
                                                    "bottom": "0",
                                                    "left": "0",
                                                    "isLinked": false
                                                },
                                                "elementskit_menu_item_border_first_child_color": "#02010100",
                                                "sub_panel_padding": {
                                                    "unit": "px",
                                                    "top": "20",
                                                    "right": "0",
                                                    "bottom": "20",
                                                    "left": "0",
                                                    "isLinked": false
                                                },
                                                "sub_panel_padding_tablet": {
                                                    "unit": "px",
                                                    "top": "10",
                                                    "right": "0",
                                                    "bottom": "10",
                                                    "left": "30",
                                                    "isLinked": false
                                                },
                                                "elementskit_panel_submenu_border_border": "solid",
                                                "elementskit_panel_submenu_border_width_tablet": {
                                                    "unit": "px",
                                                    "top": "0",
                                                    "right": "0",
                                                    "bottom": "0",
                                                    "left": "0",
                                                    "isLinked": false
                                                },
                                                "elementskit_submenu_container_background_background": "classic",
                                                "elementskit_submenu_panel_border_radius_tablet": {
                                                    "unit": "px",
                                                    "top": "0",
                                                    "right": "0",
                                                    "bottom": "0",
                                                    "left": "0",
                                                    "isLinked": false
                                                },
                                                "elementskit_menu_toggle_icon_position_tablet": "right",
                                                "elementskit_menu_toggle_spacing_tablet": {
                                                    "unit": "px",
                                                    "top": "0",
                                                    "right": "0",
                                                    "bottom": "0",
                                                    "left": "0",
                                                    "isLinked": false
                                                },
                                                "elementskit_menu_open_typography_tablet": {
                                                    "unit": "px",
                                                    "size": 25,
                                                    "sizes": []
                                                },
                                                "elementskit_menu_toggle_background_background": "classic",
                                                "elementskit_menu_toggle_background_color": "#02010100",
                                                "elementskit_menu_toggle_border_border": "solid",
                                                "elementskit_menu_toggle_border_width_tablet": {
                                                    "unit": "px",
                                                    "top": "0",
                                                    "right": "0",
                                                    "bottom": "0",
                                                    "left": "0",
                                                    "isLinked": false
                                                },
                                                "elementskit_menu_toggle_border_color": "#02010100",
                                                "elementskit_menu_close_spacing_tablet": {
                                                    "unit": "px",
                                                    "top": "0",
                                                    "right": "0",
                                                    "bottom": "0",
                                                    "left": "0",
                                                    "isLinked": false
                                                },
                                                "elementskit_menu_close_border_radius_tablet": {
                                                    "unit": "px",
                                                    "size": 0,
                                                    "sizes": []
                                                },
                                                "elementskit_menu_close_background_background": "classic",
                                                "elementskit_menu_close_background_color": "#FFFFFF00",
                                                "elementskit_menu_close_border_border": "solid",
                                                "elementskit_menu_close_border_width_tablet": {
                                                    "unit": "px",
                                                    "top": "0",
                                                    "right": "0",
                                                    "bottom": "0",
                                                    "left": "0",
                                                    "isLinked": false
                                                },
                                                "elementskit_menu_close_border_color": "#02010100",
                                                "__globals__": {
                                                    "elementskit_content_typography_typography": "globals\/typography?id=007f4bf",
                                                    "elementskit_menu_item_typography_typography": "globals\/typography?id=f8c49fb",
                                                    "elementskit_style_tab_submenu_indicator_color_tablet": "",
                                                    "elementskit_submenu_item_color_tablet": "",
                                                    "elementskit_menu_close_typography_typography": "globals\/typography?id=accent",
                                                    "elementskit_style_tab_submenu_indicator_color": "",
                                                    "elementskit_menu_toggle_icon_color_hover": "globals\/colors?id=accent",
                                                    "elementskit_item_background_hover_color": "",
                                                    "elementskit_item_color_hover_tablet": "",
                                                    "elementskit_menu_close_icon_color_hover": "globals\/colors?id=accent",
                                                    "elementskit_item_color_hover": "",
                                                    "elementskit_item_text_color_hover": "",
                                                    "elementskit_nav_menu_active_text_color": "",
                                                    "elementskit_submenu_item_color": "",
                                                    "elementskit_nav_sub_menu_active_text_color": "",
                                                    "elementskit_menu_text_color_tablet": "",
                                                    "elementskit_nav_menu_active_text_color_tablet": "",
                                                    "elementskit_item_text_color_hover_tablet": "",
                                                    "elementskit_nav_sub_menu_active_text_color_tablet": "",
                                                    "elementskit_menu_toggle_icon_color": "",
                                                    "elementskit_menu_close_icon_color": "globals\/colors?id=accent",
                                                    "elementskit_menubar_background_color": "",
                                                    "elementskit_panel_submenu_border_color": "globals\/colors?id=primary",
                                                    "elementskit_submenu_container_background_color": ""
                                                },
                                                "ekit_submenu_indicator_spacing": {
                                                    "unit": "px",
                                                    "top": "2",
                                                    "right": "0",
                                                    "bottom": "0",
                                                    "left": "15",
                                                    "isLinked": false
                                                },
                                                "elementskit_panel_submenu_border_width": {
                                                    "unit": "px",
                                                    "top": "0",
                                                    "right": "0",
                                                    "bottom": "0",
                                                    "left": "0",
                                                    "isLinked": false
                                                },
                                                "elementskit_menu_toggle_icon_color": "#FFFFFF",
                                                "elementskit_menu_open_typography_mobile": {
                                                    "unit": "px",
                                                    "size": 25,
                                                    "sizes": []
                                                },
                                                "_margin_mobile": {
                                                    "unit": "px",
                                                    "top": "0",
                                                    "right": "-20",
                                                    "bottom": "0",
                                                    "left": "0",
                                                    "isLinked": false
                                                },
                                                "_animation": "fadeIn",
                                                "elementskit_nav_menu_logo": {
                                                    "url": "http:\/\/askproject.net\/bankai\/wp-content\/uploads\/sites\/32\/2021\/10\/logo_Asset-3_3.png",
                                                    "id": 174,
                                                    "alt": "",
                                                    "source": "library"
                                                },
                                                "elementskit_menu_text_color_tablet": "#FFFFFFC4",
                                                "elementskit_item_color_hover_tablet": "#FFFFFF",
                                                "elementskit_nav_menu_active_text_color_tablet": "#FFFFFF",
                                                "elementskit_style_tab_submenu_indicator_color": "#FFFFFF",
                                                "ekit_submenu_indicator_spacing_tablet": {
                                                    "unit": "px",
                                                    "top": "0",
                                                    "right": "0",
                                                    "bottom": "0",
                                                    "left": "200",
                                                    "isLinked": false
                                                },
                                                "ekit_submenu_indicator_spacing_mobile": {
                                                    "unit": "px",
                                                    "top": "0",
                                                    "right": "0",
                                                    "bottom": "0",
                                                    "left": "160",
                                                    "isLinked": false
                                                },
                                                "elementskit_submenu_item_spacing_tablet": {
                                                    "unit": "px",
                                                    "top": "5",
                                                    "right": "15",
                                                    "bottom": "5",
                                                    "left": "15",
                                                    "isLinked": false
                                                },
                                                "elementskit_submenu_item_color_tablet": "#FFFFFFBF",
                                                "elementskit_nav_sub_menu_active_text_color_tablet": "#FFFFFF",
                                                "elementskit_menu_close_border_width_mobile": {
                                                    "unit": "px",
                                                    "top": "0",
                                                    "right": "0",
                                                    "bottom": "0",
                                                    "left": "0",
                                                    "isLinked": false
                                                },
                                                "elementskit_mobile_menu_logo_width_tablet": {
                                                    "unit": "px",
                                                    "size": 130,
                                                    "sizes": []
                                                },
                                                "elementskit_mobile_menu_logo_margin_tablet": {
                                                    "unit": "px",
                                                    "top": "7",
                                                    "right": "0",
                                                    "bottom": "30",
                                                    "left": "25",
                                                    "isLinked": false
                                                },
                                                "elementskit_mobile_menu_logo_margin_mobile": {
                                                    "unit": "px",
                                                    "top": "7",
                                                    "right": "0",
                                                    "bottom": "20",
                                                    "left": "25",
                                                    "isLinked": false
                                                },
                                                "elementskit_menu_close_icon_color_hover": "#5846E0",
                                                "elementskit_item_color_hover": "#FFFFFF",
                                                "elementskit_nav_menu_active_text_color": "#FFFFFF",
                                                "elementskit_submenu_item_color": "#FFFFFFC2",
                                                "elementskit_item_text_color_hover": "#FFFFFF",
                                                "elementskit_nav_sub_menu_active_text_color": "#FFFFFF",
                                                "elementskit_menubar_background_color_b": "#F2295B00",
                                                "elementskit_item_background_background": "classic",
                                                "elementskit_item_background_color": "#BA474700",
                                                "elementskit_item_background_color_b": "#F2295B00",
                                                "elementskit_item_background_hover_color_b": "#F2295B00",
                                                "elementskit_nav_menu_active_bg_color_color_b": "#F2295B00",
                                                "elementskit_menu_item_background_color_b": "#F2295B00",
                                                "elementskit_submenu_container_background_color_b": "#FFFFFF",
                                                "elementskit_menu_toggle_background_image_tablet": {
                                                    "url": "http:\/\/askproject.net\/nomic\/wp-content\/uploads\/sites\/10\/2021\/07\/Artboard-1@4x.png",
                                                    "id": 751,
                                                    "alt": "",
                                                    "source": "library"
                                                },
                                                "elementskit_menu_close_typography_typography": "custom",
                                                "elementskit_menu_close_typography_font_family": "Poppins",
                                                "elementskit_menu_close_typography_font_size": {
                                                    "unit": "px",
                                                    "size": 14,
                                                    "sizes": []
                                                },
                                                "elementskit_menu_close_typography_font_size_tablet": {
                                                    "unit": "px",
                                                    "size": 14,
                                                    "sizes": []
                                                },
                                                "elementskit_menu_close_typography_font_size_mobile": {
                                                    "unit": "px",
                                                    "size": 13,
                                                    "sizes": []
                                                },
                                                "elementskit_menu_close_typography_font_weight": "400",
                                                "elementskit_menu_close_typography_letter_spacing": {
                                                    "unit": "px",
                                                    "size": 0.5,
                                                    "sizes": []
                                                },
                                                "elementskit_menu_close_background_hover_background": "classic",
                                                "elementskit_menu_close_background_hover_color": "#02010100",
                                                "elementskit_menu_close_background_image_tablet": {
                                                    "url": "http:\/\/askproject.net\/nomic\/wp-content\/uploads\/sites\/10\/2021\/07\/Artboard-1@4x.png",
                                                    "id": 751,
                                                    "alt": "",
                                                    "source": "library"
                                                },
                                                "elementskit_panel_box_shadow_box_shadow_type": "yes",
                                                "elementskit_panel_box_shadow_box_shadow": {
                                                    "horizontal": 0,
                                                    "vertical": 0,
                                                    "blur": 10,
                                                    "spread": 0,
                                                    "color": "rgba(0, 0, 0, 0)"
                                                },
                                                "_margin": {
                                                    "unit": "px",
                                                    "top": "0",
                                                    "right": "0",
                                                    "bottom": "0",
                                                    "left": "15",
                                                    "isLinked": false
                                                },
                                                "_margin_tablet": {
                                                    "unit": "px",
                                                    "top": "5",
                                                    "right": "-20",
                                                    "bottom": "0",
                                                    "left": "0",
                                                    "isLinked": false
                                                },
                                                "_padding_tablet": {
                                                    "unit": "px",
                                                    "top": "0",
                                                    "right": "0",
                                                    "bottom": "0",
                                                    "left": "0",
                                                    "isLinked": false
                                                },
                                                "elementskit_menubar_height": {
                                                    "unit": "px",
                                                    "size": 80,
                                                    "sizes": []
                                                },
                                                "elementskit_border_radius": {
                                                    "unit": "px",
                                                    "top": 0,
                                                    "right": 0,
                                                    "bottom": 0,
                                                    "left": 0,
                                                    "isLinked": true
                                                },
                                                "elementskit_submenu_panel_border_radius": {
                                                    "unit": "px",
                                                    "top": 0,
                                                    "right": 0,
                                                    "bottom": 0,
                                                    "left": 0,
                                                    "isLinked": true
                                                },
                                                "elementskit_menu_close_typography_line_height": {
                                                    "unit": "em",
                                                    "size": "",
                                                    "sizes": []
                                                },
                                                "elementskit_submenu_container_width_tablet": "200px",
                                                "elementskit_content_typography_typography": "custom",
                                                "elementskit_content_typography_font_family": "Poppins",
                                                "elementskit_content_typography_font_size": {
                                                    "unit": "px",
                                                    "size": 14,
                                                    "sizes": []
                                                },
                                                "elementskit_content_typography_font_weight": "400",
                                                "elementskit_content_typography_line_height": {
                                                    "unit": "em",
                                                    "size": "",
                                                    "sizes": []
                                                },
                                                "elementskit_panel_submenu_border_color": "#051C1D",
                                                "elementskit_submenu_container_background_color": "#0F0F0F"
                                            },
                                            "elements": [],
                                            "isInner": false,
                                            "widgetType": "ekit-nav-menu",
                                            "elType": "widget"
                                        }
                                    ],
                                    "isInner": true,
                                    "elType": "column"
                                },
                                {
                                    "id": "39c4d4b3",
                                    "settings": {
                                        "_column_size": 50,
                                        "_inline_size": 25.169,
                                        "content_position": "center",
                                        "_inline_size_tablet": 92,
                                        "_inline_size_mobile": 75,
                                        "align": "flex-end",
                                        "padding": {
                                            "unit": "px",
                                            "top": "0",
                                            "right": "0",
                                            "bottom": "0",
                                            "left": "0",
                                            "isLinked": false
                                        },
                                        "padding_tablet": {
                                            "unit": "px",
                                            "top": "0",
                                            "right": "7",
                                            "bottom": "0",
                                            "left": "0",
                                            "isLinked": false
                                        }
                                    },
                                    "elements": [
                                        {
                                            "id": "67e761a6",
                                            "settings": {
                                                "text": "Contact",
                                                "button_text_color": "#FFFFFF",
                                                "background_color": "#02010100",
                                                "text_padding_tablet": {
                                                    "unit": "px",
                                                    "top": "15",
                                                    "right": "40",
                                                    "bottom": "15",
                                                    "left": "0",
                                                    "isLinked": false
                                                },
                                                "_element_width": "auto",
                                                "hide_mobile": "hidden-mobile",
                                                "__globals__": {
                                                    "typography_typography": "globals\/typography?id=accent",
                                                    "hover_color": "globals\/colors?id=accent"
                                                },
                                                "border_border": "solid",
                                                "border_width": {
                                                    "unit": "px",
                                                    "top": "0",
                                                    "right": "0",
                                                    "bottom": "0",
                                                    "left": "0",
                                                    "isLinked": false
                                                },
                                                "border_radius": {
                                                    "unit": "px",
                                                    "top": "0",
                                                    "right": "0",
                                                    "bottom": "0",
                                                    "left": "0",
                                                    "isLinked": false
                                                },
                                                "text_padding": {
                                                    "unit": "px",
                                                    "top": "0",
                                                    "right": "35",
                                                    "bottom": "0",
                                                    "left": "0",
                                                    "isLinked": false
                                                },
                                                "link": {
                                                    "url": "http:\/\/askproject.net\/bankai\/contact\/",
                                                    "is_external": "",
                                                    "nofollow": "",
                                                    "custom_attributes": ""
                                                }
                                            },
                                            "elements": [],
                                            "isInner": false,
                                            "widgetType": "button",
                                            "elType": "widget"
                                        },
                                        {
                                            "id": "7ee02db7",
                                            "settings": {
                                                "text": "Log In",
                                                "typography_typography": "custom",
                                                "typography_font_family": "Poppins",
                                                "typography_font_size": {
                                                    "unit": "px",
                                                    "size": 14,
                                                    "sizes": []
                                                },
                                                "typography_font_size_tablet": {
                                                    "unit": "px",
                                                    "size": 14,
                                                    "sizes": []
                                                },
                                                "typography_font_size_mobile": {
                                                    "unit": "px",
                                                    "size": 13,
                                                    "sizes": []
                                                },
                                                "typography_font_weight": "400",
                                                "button_text_color": "#FFFFFF",
                                                "background_color": "#5846E000",
                                                "hover_color": "#FFFFFF",
                                                "border_border": "solid",
                                                "border_width": {
                                                    "unit": "px",
                                                    "top": "2",
                                                    "right": "2",
                                                    "bottom": "2",
                                                    "left": "2",
                                                    "isLinked": true
                                                },
                                                "border_color": "#5846E0",
                                                "border_radius": {
                                                    "unit": "px",
                                                    "top": "2",
                                                    "right": "2",
                                                    "bottom": "2",
                                                    "left": "2",
                                                    "isLinked": true
                                                },
                                                "text_padding": {
                                                    "unit": "px",
                                                    "top": "16",
                                                    "right": "32",
                                                    "bottom": "16",
                                                    "left": "32",
                                                    "isLinked": false
                                                },
                                                "text_padding_tablet": {
                                                    "unit": "px",
                                                    "top": "15",
                                                    "right": "32",
                                                    "bottom": "15",
                                                    "left": "32",
                                                    "isLinked": false
                                                },
                                                "_element_width": "auto",
                                                "hide_mobile": "hidden-mobile",
                                                "__globals__": {
                                                    "typography_typography": "globals\/typography?id=accent",
                                                    "hover_color": "",
                                                    "background_color": "",
                                                    "border_color": "globals\/colors?id=accent",
                                                    "button_background_hover_color": "globals\/colors?id=accent"
                                                }
                                            },
                                            "elements": [],
                                            "isInner": false,
                                            "widgetType": "button",
                                            "elType": "widget"
                                        }
                                    ],
                                    "isInner": true,
                                    "elType": "column"
                                }
                            ],
                            "isInner": true,
                            "elType": "section"
                        }
                    ],
                    "isInner": false,
                    "elType": "column"
                }
            ],
            "isInner": false,
            "elType": "section"
        }
    ],
    "page_settings": {
        "hide_title": "yes",
        "background_background": "classic",
        "__globals__": {
            "background_color": "globals\/colors?id=secondary"
        },
        "template": "elementor_canvas"
    }
}